cat/cafe/api_models/__init__.py
cat/cafe/api_models/annotations.py
cat/cafe/api_models/datasets.py
cat/cafe/api_models/experiments.py
cat/cafe/api_models/traces.py
cat/cafe/client/__init__.py
cat/cafe/client/client.py
cat_cafe_client-0.0.3.dist-info/METADATA
cat_cafe_client-0.0.3.dist-info/WHEEL
cat_cafe_client-0.0.3.dist-info/RECORD
