Metadata-Version: 2.4
Name: cat-cafe-client
Version: 0.0.3
Summary: Python client for CAT Cafe - Continuous Alignment Testing platform for LLM observability
Author-email: Kurtis Seebaldt <kurtisseebaldt@artium.ai>
Requires-Python: >=3.12
Requires-Dist: httpx>=0.24.0
Requires-Dist: typing-extensions>=4.0.0
